sfdata_cli_launcher.py
pyarmor_runtime_000000/__init__.py
pyarmor_runtime_000000/pyarmor_runtime.pyd
sfdata/__init__.py
sfdata/__main__.py
sfdata/launcher.py
sfdata/cli/__init__.py
sfdata/cli/main.py
sfdata/core/__init__.py
sfdata/core/bulk_api.py
sfdata/core/enrich_engine.py
sfdata/core/export_engine.py
sfdata/core/import_engine.py
sfdata/core/plugin_hooks.py
sfdata/core/plugin_manager.py
sfdata/core/sf_connection.py
sfdata/plugins/__init__.py
sfdata/plugins/builtin_documents.py
sfdata/plugins/builtin_documenttemplate.py
sfdata/schemas/__init__.py
sfdata/storage/__init__.py
sfdata/utils/__init__.py
sfdata/utils/config.py
sfdata/utils/logging.py
sfdata/utils/schema_cache.py
sfdata/utils/sfdx_auth.py
sfdatamigrate-0.1.9.dist-info/licenses/LICENSE
sfdatamigrate-0.1.9.dist-info/METADATA
sfdatamigrate-0.1.9.dist-info/WHEEL
sfdatamigrate-0.1.9.dist-info/entry_points.txt
sfdatamigrate-0.1.9.dist-info/top_level.txt
sfdatamigrate-0.1.9.dist-info/RECORD
